datarec/__init__.py
datarec/data/__init__.py
datarec/data/characteristics.py
datarec/data/datarec_builder.py
datarec/data/dataset.py
datarec/data/download.py
datarec/data/graph.py
datarec/data/resource.py
datarec/data/source.py
datarec/data/topological_characteristics.py
datarec/data/torch_dataset.py
datarec/data/utils.py
datarec/datasets/__init__.py
datarec/datasets/base.py
datarec/datasets/examples.py
datarec/io/__init__.py
datarec/io/cache.py
datarec/io/paths.py
datarec/io/rawdata.py
datarec/io/utils.py
datarec/io/frameworks/__init__.py
datarec/io/frameworks/exporter.py
datarec/io/frameworks/manager.py
datarec/io/frameworks/clayrs/__init__.py
datarec/io/frameworks/clayrs/clayrs.py
datarec/io/frameworks/cornac/__init__.py
datarec/io/frameworks/cornac/cornac.py
datarec/io/frameworks/daisyrec/__init__.py
datarec/io/frameworks/daisyrec/daisyrec.py
datarec/io/frameworks/daisyrec/loader.py
datarec/io/frameworks/elliot/__init__.py
datarec/io/frameworks/elliot/datarec_config.py
datarec/io/frameworks/elliot/elliot.py
datarec/io/frameworks/lenskit/__init__.py
datarec/io/frameworks/lenskit/lenskit.py
datarec/io/frameworks/recbole/__init__.py
datarec/io/frameworks/recbole/recbole.py
datarec/io/frameworks/rechorus/__init__.py
datarec/io/frameworks/rechorus/rechorus.py
datarec/io/frameworks/recommenders/__init__.py
datarec/io/frameworks/recommenders/recommenders.py
datarec/io/frameworks/recpack/__init__.py
datarec/io/frameworks/recpack/copy_me_in__init__.py
datarec/io/frameworks/recpack/datarec.py
datarec/io/frameworks/recpack/recpack.py
datarec/io/readers/__init__.py
datarec/io/readers/_decorators.py
datarec/io/readers/sequences/__init__.py
datarec/io/readers/sequences/json.py
datarec/io/readers/sequences/tabular.py
datarec/io/readers/transactions/__init__.py
datarec/io/readers/transactions/blocks.py
datarec/io/readers/transactions/json.py
datarec/io/readers/transactions/jsonl.py
datarec/io/readers/transactions/tabular.py
datarec/io/writers/__init__.py
datarec_lib-1.5.0.dist-info/licenses/LICENSE.txt
datarec_lib-1.5.0.dist-info/METADATA
datarec_lib-1.5.0.dist-info/WHEEL
datarec_lib-1.5.0.dist-info/top_level.txt
datarec_lib-1.5.0.dist-info/RECORD
