Metadata-Version: 2.4
Name: datarec-lib
Version: 1.5.0
Summary: Standardized & reproducible data management for recommender systems.
Author-email: Alberto Carlo Maria Mancino <alberto.mancino@poliba.it>, Salvatore Bufi <salvatore.bufi@poliba.it>, Angela Di Fazio <angela.difazio@poliba.it>, Daniele Malitesta <daniele.malitesta@centralesupelec.fr>, Antonio Ferrara <antonio.ferrara@poliba.it>, Claudio Pomo <claudio.pomo@poliba.it>, Tommaso Di Noia <tommaso.dinoia@poliba.it>
License: MIT
Project-URL: Homepage, https://sisinflab.github.io/DataRec/
Project-URL: Repository, https://github.com/sisinflab/DataRec
Project-URL: Issues, https://github.com/sisinflab/DataRec/issues
Keywords: recommender-systems,data,ml,etl
Classifier: Programming Language :: Python :: 3
Classifier: Programming Language :: Python :: 3 :: Only
Classifier: Programming Language :: Python :: 3.9
Classifier: Operating System :: OS Independent
Classifier: Intended Audience :: Developers
Classifier: Topic :: Scientific/Engineering :: Artificial Intelligence
Requires-Python: <3.15,>=3.9
License-File: LICENSE.txt
Requires-Dist: numpy<3,>=1.23
Requires-Dist: pandas<3,>=2.3
Requires-Dist: scikit-learn<2,>=1.6
Requires-Dist: tqdm<5,>=4.64
Requires-Dist: gdown<5,>=4.7
Requires-Dist: requests<3,>=2.28
Requires-Dist: py7zr<1,>=0.22
Requires-Dist: PyYAML<7,>=6.0
Requires-Dist: platformdirs<5,>=4.4.0
Requires-Dist: appdirs<2,>=1.4.4
Requires-Dist: typing_extensions
Requires-Dist: networkx<4,>=3.2
Requires-Dist: python-igraph<2,>=1.0
Requires-Dist: PySocks<2,>=1.7
Provides-Extra: torch
Requires-Dist: torch>=2.0.0; extra == "torch"
Provides-Extra: dev
Requires-Dist: pytest<9,>=8.4; extra == "dev"
Requires-Dist: build<2,>=1.3; extra == "dev"
Requires-Dist: twine<7,>=6.2; extra == "dev"
Requires-Dist: pip-chill<2,>=1.0; extra == "dev"
Provides-Extra: docs
Requires-Dist: babel; extra == "docs"
Requires-Dist: backrefs; extra == "docs"
Requires-Dist: certifi; extra == "docs"
Requires-Dist: charset-normalizer; extra == "docs"
Requires-Dist: click; extra == "docs"
Requires-Dist: colorama; extra == "docs"
Requires-Dist: ghp-import; extra == "docs"
Requires-Dist: griffe; extra == "docs"
Requires-Dist: idna; extra == "docs"
Requires-Dist: Jinja2; extra == "docs"
Requires-Dist: Markdown; extra == "docs"
Requires-Dist: MarkupSafe; extra == "docs"
Requires-Dist: mergedeep; extra == "docs"
Requires-Dist: mkdocs; extra == "docs"
Requires-Dist: mkdocs-autorefs; extra == "docs"
Requires-Dist: mkdocs-get-deps; extra == "docs"
Requires-Dist: mkdocs-material; extra == "docs"
Requires-Dist: mkdocs-material-extensions; extra == "docs"
Requires-Dist: mkdocs-section-index; extra == "docs"
Requires-Dist: mkdocstrings; extra == "docs"
Requires-Dist: mkdocstrings-python; extra == "docs"
Requires-Dist: packaging; extra == "docs"
Requires-Dist: paginate; extra == "docs"
Requires-Dist: pathspec; extra == "docs"
Requires-Dist: platformdirs; extra == "docs"
Requires-Dist: Pygments; extra == "docs"
Requires-Dist: pymdown-extensions; extra == "docs"
Requires-Dist: python-dateutil; extra == "docs"
Requires-Dist: PyYAML; extra == "docs"
Requires-Dist: pyyaml_env_tag; extra == "docs"
Requires-Dist: requests; extra == "docs"
Requires-Dist: six; extra == "docs"
Requires-Dist: urllib3; extra == "docs"
Requires-Dist: watchdog; extra == "docs"
Dynamic: license-file
